greenviz.py
greenviz-2.0.2.data/data/bg5.jpg
greenviz-2.0.2.data/data/raja12.jpeg
greenviz-2.0.2.data/data/resized achuth pic.jpeg
greenviz-2.0.2.data/data/shiridi pic rezied.jpeg
greenviz-2.0.2.dist-info/LICENSE.txt
greenviz-2.0.2.dist-info/License (2).txt
greenviz-2.0.2.dist-info/METADATA
greenviz-2.0.2.dist-info/WHEEL
greenviz-2.0.2.dist-info/top_level.txt
greenviz-2.0.2.dist-info/RECORD
