Metadata-Version: 2.1
Name: greenviz
Version: 2.0.2
Summary: Greenviz is a package to support students/ users, who face difficulty in comprehending machine learning and data analytics algorithms. Greenviz uses the python programming constructs to run various learning algorithms. Hence users can understand working of various learning algorithms practically and visually.
Home-page: https://github.com/RRajaSubramanian/Greenviz
Author: R.raja subramanian
Author-email: rajasubramanian.r1@gmail.com
License: UNKNOWN
Platform: UNKNOWN
Requires-Dist: pillow
Requires-Dist: matplotlib
Requires-Dist: sklearn
Requires-Dist: pydotplus
Requires-Dist: seaborn
Requires-Dist: dnspython
Requires-Dist: pandas
Requires-Dist: pymongo
Requires-Dist: numpy
Requires-Dist: IPython
Requires-Dist: graphviz
